allauth_jinja/account/__init__.py
allauth_jinja/account/templatetags/__init__.py
allauth_jinja/account/templatetags/account.py
allauth_jinja/jinja2/__init__.py
allauth_jinja/jinja2/account/account_inactive.jinja
allauth_jinja/jinja2/account/base.jinja
allauth_jinja/jinja2/account/email/account_already_exists_message.txt
allauth_jinja/jinja2/account/email/account_already_exists_subject.txt
allauth_jinja/jinja2/account/email/base_message.txt
allauth_jinja/jinja2/account/email/email_confirmation_message.txt
allauth_jinja/jinja2/account/email/email_confirmation_signup_message.txt
allauth_jinja/jinja2/account/email/email_confirmation_signup_subject.txt
allauth_jinja/jinja2/account/email/email_confirmation_subject.txt
allauth_jinja/jinja2/account/email/password_reset_key_message.txt
allauth_jinja/jinja2/account/email/password_reset_key_subject.txt
allauth_jinja/jinja2/account/email/unknown_account_message.txt
allauth_jinja/jinja2/account/email/unknown_account_subject.txt
allauth_jinja/jinja2/account/login.jinja
allauth_jinja/jinja2/account/logout.jinja
allauth_jinja/jinja2/account/messages/cannot_delete_primary_email.txt
allauth_jinja/jinja2/account/messages/email_confirmation_failed.txt
allauth_jinja/jinja2/account/messages/email_confirmation_sent.txt
allauth_jinja/jinja2/account/messages/email_confirmed.txt
allauth_jinja/jinja2/account/messages/email_deleted.txt
allauth_jinja/jinja2/account/messages/logged_in.txt
allauth_jinja/jinja2/account/messages/logged_out.txt
allauth_jinja/jinja2/account/messages/password_changed.txt
allauth_jinja/jinja2/account/messages/password_set.txt
allauth_jinja/jinja2/account/messages/primary_email_set.txt
allauth_jinja/jinja2/account/messages/unverified_primary_email.txt
allauth_jinja/jinja2/account/password_change.jinja
allauth_jinja/jinja2/account/password_reset.jinja
allauth_jinja/jinja2/account/password_reset_done.jinja
allauth_jinja/jinja2/account/password_reset_from_key.jinja
allauth_jinja-0.0.3.dist-info/LICENSE
allauth_jinja-0.0.3.dist-info/METADATA
allauth_jinja-0.0.3.dist-info/WHEEL
allauth_jinja-0.0.3.dist-info/RECORD
