Metadata-Version: 2.1
Name: allauth-jinja
Version: 0.0.3
Summary: 
Author: Eddie Cohen
Author-email: eddie@lightmatter.com
Requires-Python: >=3.10,<4.0
Classifier: Programming Language :: Python :: 3
Classifier: Programming Language :: Python :: 3.10
Classifier: Programming Language :: Python :: 3.11
Requires-Dist: django (>=4.2.5,<5.0.0)
Requires-Dist: django-allauth (>=0.56.1,<0.57.0)
Requires-Dist: django-jinja (>=2.11.0,<3.0.0)
